CHANGELOG
INSTALL
LICENSE
MANIFEST.in
README
TODO
setup.cfg
setup.py
Pynu.egg-info/PKG-INFO
Pynu.egg-info/SOURCES.txt
Pynu.egg-info/dependency_links.txt
Pynu.egg-info/requires.txt
Pynu.egg-info/top_level.txt
docs/conf.py
docs/index.rst
pynu/__init__.py
pynu/graph.py
pynu/node.py
pynu/tree.py