Metadata-Version: 1.1
Name: Pynu
Version: 0.1.4
Summary: Pynu provides utility classes that offer basic graph tree traversal and manipulation functionality.
Home-page: http://github.com/bebraw/pynu
Author: Juho Vepsäläinen
Author-email: bebraw@gmail.com
License: MIT
Keywords: graph,nodes
Platform: UNKNOWN
Classifier: Development Status :: 3 - Alpha
Classifier: Intended Audience :: Developers
Classifier: License :: OSI Approved :: MIT License
Classifier: Natural Language :: English
Classifier: Operating System :: OS Independent
Classifier: Programming Language :: Python :: 2.6
Classifier: Topic :: Scientific/Engineering
Classifier: Topic :: Software Development
